sbn/brokers.py
sbn/caching.py
sbn/clients.py
sbn/command.py
sbn/handler.py
sbn/methods.py
sbn/objects.py
sbn/package.py
sbn/serials.py
sbn/threads.py
sbn/utility.py
sbn/workdir.py
sbn/modules/flt.py
sbn/modules/fnd.py
sbn/modules/irc.py
sbn/modules/log.py
sbn/modules/lst.py
sbn/modules/mdl.py
sbn/modules/mod.py
sbn/modules/pth.py
sbn/modules/req.py
sbn/modules/rss.py
sbn/modules/sil.py
sbn/modules/slg.py
sbn/modules/tdo.py
sbn/modules/thr.py
sbn/modules/upt.py
sbn/modules/web.py
sbn/network/main.py
sbn/network/html/about.html
sbn/network/html/evidence.html
sbn/network/html/genindex-all.html
sbn/network/html/genindex.html
sbn/network/html/guilty.html
sbn/network/html/index.html
sbn/network/html/manual.html
sbn/network/html/objects.inv
sbn/network/html/pubchem.html
sbn/network/html/reconsider.html
sbn/network/html/request.html
sbn/network/html/robots.txt
sbn/network/html/search.html
sbn/network/html/searchindex.js
sbn/network/html/writings.html
sbn/network/html/_images/ECHAabilify.png
sbn/network/html/_images/ECHAclozapine.png
sbn/network/html/_images/ECHAhaldol.png
sbn/network/html/_images/ECHAzyprexa.png
sbn/network/html/_images/OTP111.png
sbn/network/html/_images/OTP222.png
sbn/network/html/_images/abilifypubchem.png
sbn/network/html/_images/ack3.png
sbn/network/html/_images/bevestigd.jpg
sbn/network/html/_images/clozapinepubchem.png
sbn/network/html/_images/genocide.png
sbn/network/html/_images/haldolpubchem.png
sbn/network/html/_images/informed.jpg
sbn/network/html/_images/kamer2.png
sbn/network/html/_images/skull3.png
sbn/network/html/_images/zyprexapubchem.png
sbn/network/html/_static/alabaster.css
sbn/network/html/_static/basic.css
sbn/network/html/_static/custom.css
sbn/network/html/_static/doctools.js
sbn/network/html/_static/documentation_options.js
sbn/network/html/_static/file.png
sbn/network/html/_static/genocide.css
sbn/network/html/_static/language_data.js
sbn/network/html/_static/minus.png
sbn/network/html/_static/opensearch.xml
sbn-143.dist-info/METADATA
sbn-143.dist-info/WHEEL
sbn-143.dist-info/entry_points.txt
sbn-143.dist-info/top_level.txt
sbn-143.dist-info/RECORD
