Metadata-Version: 2.4
Name: sbn
Version: 143
Summary: Since 4 March 2019
Author-email: Bart Thate <bthate@dds.nl>
License-Expression: Unlicense
Project-URL: home, https://pypi.org/project/sbn
Project-URL: bugs, https://github.com/bthate/sbn/issues
Project-URL: source, https://github.com/bthate/sbn
Classifier: Development Status :: 3 - Alpha
Classifier: Operating System :: Unix
Classifier: Programming Language :: Python
Classifier: Topic :: Utilities
